py37_workspace/__init__.py
py37_workspace/async01.py
py37_workspace/async02.py
py37_workspace/async03.py
py37_workspace/async04.py
py37_workspace/async05.py
py37_workspace-0.1.0.dist-info/WHEEL
py37_workspace-0.1.0.dist-info/METADATA
py37_workspace-0.1.0.dist-info/RECORD
