Metadata-Version: 2.1
Name: py37-workspace
Version: 0.1.0
Summary: 
Author: Your Name
Author-email: you@example.com
Requires-Python: >=3.6,<4.0
Classifier: Programming Language :: Python :: 3
Classifier: Programming Language :: Python :: 3.6
Classifier: Programming Language :: Python :: 3.7
Requires-Dist: Alfred-Workflow (>=1.37,<2.0)
Requires-Dist: ipython (>=7.9,<8.0)
Requires-Dist: jupyter (>=1.0,<2.0)
Requires-Dist: openpyxl (>=3.0,<4.0)
Requires-Dist: pyppeteer (>=0.0.25,<0.0.26)
Requires-Dist: requests (>=2.22,<3.0)
